fusilli/__init__.py
fusilli/_version.py
fusilli/data.py
fusilli/eval.py
fusilli/train.py
fusilli/fusionmodels/__init__.py
fusilli/fusionmodels/base_model.py
fusilli/fusionmodels/tabularfusion/__init__.py
fusilli/fusionmodels/tabularfusion/activation.py
fusilli/fusionmodels/tabularfusion/attention_and_activation.py
fusilli/fusionmodels/tabularfusion/attention_weighted_GNN.py
fusilli/fusionmodels/tabularfusion/channelwise_att.py
fusilli/fusionmodels/tabularfusion/concat_data.py
fusilli/fusionmodels/tabularfusion/concat_feature_maps.py
fusilli/fusionmodels/tabularfusion/crossmodal_att.py
fusilli/fusionmodels/tabularfusion/decision.py
fusilli/fusionmodels/tabularfusion/edge_corr_gnn.py
fusilli/fusionmodels/tabularfusion/mcvae_model.py
fusilli/fusionmodels/tabularimagefusion/__init__.py
fusilli/fusionmodels/tabularimagefusion/channelwise_att.py
fusilli/fusionmodels/tabularimagefusion/concat_img_latent_tab_doubleloss.py
fusilli/fusionmodels/tabularimagefusion/concat_img_latent_tab_doubletrain.py
fusilli/fusionmodels/tabularimagefusion/concat_img_maps_tabular_data.py
fusilli/fusionmodels/tabularimagefusion/concat_img_maps_tabular_maps.py
fusilli/fusionmodels/tabularimagefusion/crossmodal_att.py
fusilli/fusionmodels/tabularimagefusion/decision.py
fusilli/fusionmodels/tabularimagefusion/denoise_tab_img_maps.py
fusilli/fusionmodels/unimodal/__init__.py
fusilli/fusionmodels/unimodal/image.py
fusilli/fusionmodels/unimodal/tabular1.py
fusilli/fusionmodels/unimodal/tabular2.py
fusilli/utils/__init__.py
fusilli/utils/check_model_validity.py
fusilli/utils/csv_loss_plotter.py
fusilli/utils/metrics_utils.py
fusilli/utils/model_chooser.py
fusilli/utils/model_modifier.py
fusilli/utils/training_utils.py
fusilli/utils/mcvae/setup.py
fusilli/utils/mcvae/examples/mcvae/sparse_vs_non_sparse.py
fusilli/utils/mcvae/src/__init__.py
fusilli/utils/mcvae/src/mcvae/__init__.py
fusilli/utils/mcvae/src/mcvae/datasets/__init__.py
fusilli/utils/mcvae/src/mcvae/datasets/synthetic.py
fusilli-1.2.3.dist-info/LICENSE
fusilli-1.2.3.dist-info/METADATA
fusilli-1.2.3.dist-info/WHEEL
fusilli-1.2.3.dist-info/top_level.txt
fusilli-1.2.3.dist-info/RECORD
