Metadata-Version: 2.1
Name: fusilli
Version: 1.2.3
Summary: Comparing multi-modal data fusion methods. Don't be silly, use Fusilli!
Author-email: Florence J Townend <f.j.townend@live.com>
Keywords: multi-modal,machine learning,MRI,data fusion,multi-view,graph neural network,attention,VAE
Classifier: Programming Language :: Python :: 3
Classifier: License :: OSI Approved :: MIT License
Classifier: Operating System :: OS Independent
Requires-Python: >=3.7
License-File: LICENSE
Requires-Dist: lightning ~=2.0
Requires-Dist: matplotlib ~=3.5
Requires-Dist: numpy ~=1.25
Requires-Dist: pandas ~=2.0
Requires-Dist: scikit-learn ~=1.0
Requires-Dist: setuptools ~=68.0
Requires-Dist: torch ~=2.0
Requires-Dist: torch-geometric ~=2.0
Requires-Dist: torchmetrics ~=0.0
Requires-Dist: tqdm ~=4.0
Requires-Dist: wandb ~=0.0
Provides-Extra: docs
Requires-Dist: protobuf ~=3.0 ; extra == 'docs'
Requires-Dist: sphinx ; extra == 'docs'
Requires-Dist: sphinx-gallery ; extra == 'docs'
Requires-Dist: sphinx-rtd-theme ; extra == 'docs'
Requires-Dist: sphinx-wagtail-theme ; extra == 'docs'
Requires-Dist: sphinxcontrib-applehelp ; extra == 'docs'
Requires-Dist: sphinxcontrib-devhelp ; extra == 'docs'
Requires-Dist: sphinxcontrib-htmlhelp ; extra == 'docs'
Requires-Dist: sphinxcontrib-jquery ; extra == 'docs'
Requires-Dist: sphinxcontrib-jsmath ; extra == 'docs'
Requires-Dist: sphinxcontrib-qthelp ; extra == 'docs'
Requires-Dist: sphinxcontrib-serializinghtml ; extra == 'docs'
Requires-Dist: renku-sphinx-theme ; extra == 'docs'
